liquidbase/__init__.py
liquidbase/api/__init__.py
liquidbase/api/errors.py
liquidbase/api/memory.py
liquidbase/constants.py
liquidbase/db/__init__.py
liquidbase/db/liquid_db.py
liquidbase/db/model.py
liquidbase/store.py
liquidbase-0.1.2.dist-info/WHEEL
liquidbase-0.1.2.dist-info/METADATA
liquidbase-0.1.2.dist-info/RECORD
